openapiclient/__init__.py
openapiclient/client.py
httpx_openapi_gen-0.1.0.dist-info/METADATA
httpx_openapi_gen-0.1.0.dist-info/WHEEL
httpx_openapi_gen-0.1.0.dist-info/top_level.txt
httpx_openapi_gen-0.1.0.dist-info/RECORD
