Metadata-Version: 2.2
Name: httpx-openapi-gen
Version: 0.1.0
Summary: A Python client for OpenAPI specifications using httpx
Home-page: https://github.com/lloydzhou/openapiclient
Author: lloydzhou
Author-email: lloydzhou@qq.com
Classifier: Programming Language :: Python :: 3
Classifier: License :: OSI Approved :: MIT License
Classifier: Operating System :: OS Independent
Requires-Python: >=3.7
Requires-Dist: httpx>=0.23.0
Requires-Dist: pyyaml>=6.0
Dynamic: author
Dynamic: author-email
Dynamic: classifier
Dynamic: description
Dynamic: description-content-type
Dynamic: home-page
Dynamic: requires-dist
Dynamic: requires-python
Dynamic: summary
